LICENSE
README.md
avian_lwma-0.1.0.dist-info/RECORD
avian_lwma-0.1.0.dist-info/WHEEL
avian_lwma-0.1.0.dist-info/METADATA
avian_lwma-0.1.0.dist-info/licenses/LICENSE
avian_lwma/_core.so
avian_lwma/__init__.py
