Metadata-Version: 2.2
Name: avian_lwma
Version: 0.1.0
Summary: LWMA target calculator for dual-algo Avian forks (pybind11)
Author: avian_lwma contributors
Classifier: Programming Language :: Python :: 3
Classifier: Programming Language :: C++
Classifier: License :: OSI Approved :: MIT License
Classifier: Operating System :: OS Independent
Requires-Python: >=3.12
